{
  "summary": "In this lively clip from a rugby training session, players are engaged in a casual yet competitive atmosphere as they discuss the game and their teammates. The dialogue is filled with playful banter, highlighting the camaraderie among the players. Notably, one player expresses admiration for another's toughness, showcasing the respect and recognition of skill within the team. The lighthearted exchanges and friendly teasing create a sense of community and shared passion for the sport.",
  "setting": "A rugby training field, bustling with activity and energy as players interact during a break in the action.",
  "participants": "A group of rugby players, casually discussing their teammates and the ongoing game.",
  "key_moments": [
    "Dude, what a bomb.",
    "He comes to touch. He's a G.",
    "What position does he play? Oh, he plays A."
  ],
  "tone": "The overall mood is playful and energetic, reflecting the camaraderie and competitive spirit of the team.",
  "filename": "M2U00301.srt",
  "folder": "pre_sort_broll_01"
}