{
  "summary": "In this brief clip, a group of players is gathered during a rugby training session, discussing their strategy and approach to the drills. The speaker emphasizes a slow and deliberate pace, indicating a focus on technique and teamwork. The camaraderie among the players is evident as they prepare to execute their plans. This moment captures the essence of training, where communication and collaboration are key to success.",
  "setting": "A rugby training field, with players gathered in a huddle.",
  "participants": "A group of rugby players, with one speaker leading the discussion.",
  "key_moments": [
    "Focus on technique and teamwork",
    "Emphasis on a slow and deliberate pace"
  ],
  "tone": "Collaborative and focused",
  "filename": "M2U00243.srt",
  "folder": "pre_sort_broll_01"
}