{
  "summary": "The clip captures an energetic moment during a rugby training session, where team members enthusiastically cheer each other on. The camaraderie among the players is evident as they rally behind their team, the Eagles, with chants of encouragement. A light-hearted exchange about gear showcases the team's bond and excitement for their training. The atmosphere is filled with motivation and a shared love for the sport.",
  "setting": "A rugby training field, bustling with players and the sounds of encouragement.",
  "participants": "Members of the Eagles rugby team, including players who are cheering and discussing their gear.",
  "key_moments": [
    "'Way to go Eagles, let's go!'",
    "'Fight!'",
    "'These are awesome bro.'"
  ],
  "tone": "Energetic and supportive",
  "filename": "M2U00314.srt",
  "folder": "pre_sort_broll_01"
}