{
  "summary": "In this lively training session, players are engaged in drills and light banter, showcasing their camaraderie and playful spirit. The atmosphere is sunny and energetic, with participants encouraging each other and celebrating small victories, like a well-executed pass. A notable moment occurs when one player humorously admits to looking foolish on camera, adding a lighthearted touch to the practice. The coach emphasizes the importance of keeping hands up and out during play, reinforcing key techniques for effective gameplay. Overall, the clip captures the joy and dedication of the team as they work together to improve their skills.",
  "setting": "A sunny outdoor rugby training field with players actively participating in drills.",
  "participants": "Players and a coach, including a player named Ricky.",
  "key_moments": [
    "Player jokingly admits to looking like a dummy on camera.",
    "Encouragement for a well-executed pass: 'Ricky, that was real nice.'",
    "Coach's advice: 'Hands up and out, hands up and out.'"
  ],
  "tone": "Playful and energetic, with a sense of teamwork and lightheartedness.",
  "filename": "M2U00252.srt",
  "folder": "pre_sort_broll_01"
}