{
  "summary": "The clip captures an intense moment during a rugby match, filled with enthusiastic shouts and cheers from the sidelines. Players are actively engaged in the game, with a particular focus on Joe, who receives praise for a remarkable tackle. The energy is palpable as teammates encourage each other, urging them to push harder and score. The dialogue reflects the camaraderie and competitive spirit typical of rugby culture, with a mix of excitement and frustration evident in the players' voices.",
  "setting": "A rugby field during a match, with players in action and spectators cheering from the sidelines.",
  "participants": "Unnamed players and spectators, with a focus on Joe and Aiden.",
  "key_moments": [
    "What a fucking tackle!",
    "Way to go, Joe!",
    "Come on, come on, come on.",
    "Back yourself, Aiden!"
  ],
  "tone": "Energetic and competitive, with a mix of excitement and urgency.",
  "filename": "M2U00465.srt",
  "folder": "pre_sort_broll_01"
}